frenchbee/__init__.py
frenchbee/cli.py
frenchbee/data.py
frenchbee/frenchbee.py
frenchbee/models.py
frenchbee/reese84.py
frenchbee-0.1.1.dist-info/entry_points.txt
frenchbee-0.1.1.dist-info/LICENSE
frenchbee-0.1.1.dist-info/WHEEL
frenchbee-0.1.1.dist-info/METADATA
frenchbee-0.1.1.dist-info/RECORD
