Metadata-Version: 2.1
Name: frenchbee
Version: 0.1.1
Summary: Python client for finding French Bee airline prices.
Home-page: https://github.com/minormending/frenchbee
License: MIT
Keywords: frenchbee,flights,travel
Author: Kevin Ramdath
Author-email: krpent@gmail.com
Requires-Python: >=3.8,<4.0
Classifier: License :: OSI Approved :: MIT License
Classifier: Programming Language :: Python :: 3
Classifier: Programming Language :: Python :: 3.10
Classifier: Programming Language :: Python :: 3.8
Classifier: Programming Language :: Python :: 3.9
Requires-Dist: beautifulsoup4 (>=4.11.1,<5.0.0)
Requires-Dist: jsonpath-ng (>=1.5.3,<2.0.0)
Requires-Dist: requests (>=2.27.1,<3.0.0)
Project-URL: Repository, https://github.com/minormending/frenchbee
